{"name":"7b12e5ad-a45b-47dd-a353-182c5f0b6ccf","id":"/providers/Microsoft.Flow/flows/7b12e5ad-a45b-47dd-a353-182c5f0b6ccf","type":"Microsoft.Flow/flows","properties":{"apiId":"/providers/Microsoft.PowerApps/apis/shared_logicflows","displayName":"File Unpacking","definition":{"metadata":{"workflowEntityId":null,"processAdvisorMetadata":null,"flowChargedByPaygo":null,"flowclientsuspensionreason":"None","flowclientsuspensiontime":null,"flowclientsuspensionreasondetails":null,"creator":{"id":"bf85dcd3-7cd6-4939-a085-92657b86d68b","type":"User","tenantId":"007b3d70-6166-44e3-a2c3-4152544ee6d6"},"provisioningMethod":"FromDefinition","failureAlertSubscription":true,"clientLastModifiedTime":"2025-07-04T04:15:20.7458205Z","connectionKeySavedTimeKey":"2025-07-04T04:15:20.7458205Z","creationSource":"Portal","modifiedSources":"Portal"},"$schema":"https://schema.management.azure.com/providers/Microsoft.Logic/schemas/2016-06-01/workflowdefinition.json#","contentVersion":"1.0.0.0","parameters":{"$authentication":{"defaultValue":{},"type":"SecureObject"},"$connections":{"defaultValue":{},"type":"Object"}},"triggers":{"When_a_new_email_arrives_(V3)":{"splitOn":"@triggerOutputs()?['body/value']","type":"OpenApiConnectionNotification","inputs":{"parameters":{"fetchOnlyWithAttachment":true},"host":{"apiId":"/providers/Microsoft.PowerApps/apis/shared_office365","connectionName":"shared_office365","operationId":"OnNewEmailV3"},"authentication":"@parameters('$authentication')"}}},"actions":{"For_each_1":{"foreach":"@triggerOutputs()?['body/attachments']","actions":{"Get_Attachment_(V2)":{"type":"OpenApiConnection","inputs":{"parameters":{"messageId":"@triggerOutputs()?['body/id']","attachmentId":"@item()?['id']","extractSensitivityLabel":"false","fetchSensitivityLabelMetadata":"false"},"host":{"apiId":"/providers/Microsoft.PowerApps/apis/shared_office365","connectionName":"shared_office365-1","operationId":"GetAttachment_V2"},"authentication":"@parameters('$authentication')"}},"Get_file_content":{"runAfter":{"Create_file":["Succeeded"]},"metadata":{"b!Dxr_V6UGXEO0BqgLOUrt5QfWCV0OLjVEgY_E6aHvc0O6WcKHaQ1GRL-vUFI-kt_n.015ATGU2D4BV2VPSUDEFCZGAZ7PVTPFIGA":"/Attachments/test-attachments.zip","b!Dxr_V6UGXEO0BqgLOUrt5QfWCV0OLjVEgY_E6aHvc0O6WcKHaQ1GRL-vUFI-kt_n.015ATGU2AGA256422O5VDJR5G3O5X4JTVO":"/Attachments/q_20250627081644.zip"},"type":"OpenApiConnection","inputs":{"parameters":{"id":"@outputs('Create_file')?['body/Id']","inferContentType":true},"host":{"apiId":"/providers/Microsoft.PowerApps/apis/shared_onedriveforbusiness","connectionName":"shared_onedriveforbusiness-1","operationId":"GetFileContent"},"authentication":"@parameters('$authentication')"}},"Create_file":{"runAfter":{"Get_Attachment_(V2)":["Succeeded"]},"type":"OpenApiConnection","inputs":{"parameters":{"folderPath":"/Attachments","name":"@outputs('Get_Attachment_(V2)')?['body/name']","body":"@outputs('Get_Attachment_(V2)')?['body/contentBytes']"},"host":{"apiId":"/providers/Microsoft.PowerApps/apis/shared_onedriveforbusiness","connectionName":"shared_onedriveforbusiness-1","operationId":"CreateFile"},"authentication":"@parameters('$authentication')"},"runtimeConfiguration":{"contentTransfer":{"transferMode":"Chunked"}}},"Archive_(ZIP)_-_Extract":{"runAfter":{"Get_file_content":["Succeeded"]},"type":"OpenApiConnection","inputs":{"parameters":{"operation/fileContent":"@body('Get_file_content')","operation/includeFolders":true},"host":{"apiId":"/providers/Microsoft.PowerApps/apis/shared_encodiangeneral","connectionName":"shared_encodiangeneral-2","operationId":"General_ExtractFromArchive"},"authentication":"@parameters('$authentication')"}},"For_each_2":{"foreach":"@outputs('Archive_(ZIP)_-_Extract')?['body/documents']","actions":{"Create_file_1":{"type":"OpenApiConnection","inputs":{"parameters":{"dataset":"https://birudukota.sharepoint.com/sites/InternshipSite","folderPath":"/Shared Documents/Attachments","name":"@items('For_each_2')?['fileName']","body":"@items('For_each_2')?['fileContent']"},"host":{"apiId":"/providers/Microsoft.PowerApps/apis/shared_sharepointonline","connectionName":"shared_sharepointonline","operationId":"CreateFile"},"authentication":"@parameters('$authentication')"},"runtimeConfiguration":{"contentTransfer":{"transferMode":"Chunked"}}}},"runAfter":{"Archive_(ZIP)_-_Extract":["Succeeded"]},"type":"Foreach"}},"runAfter":{},"type":"Foreach"}},"outputs":{}},"connectionReferences":{"shared_office365":{"connectionName":"shared-office365-49a8fbf0-9d8a-4ad9-912a-243e520e3655","source":"Embedded","id":"/providers/Microsoft.PowerApps/apis/shared_office365","tier":"NotSpecified","apiName":"office365","isProcessSimpleApiReferenceConversionAlreadyDone":false},"shared_office365-1":{"connectionName":"shared-office365-be8af670-6142-4a7a-8727-681ba8b8bcb7","source":"Embedded","id":"/providers/Microsoft.PowerApps/apis/shared_office365","tier":"NotSpecified","apiName":"office365","isProcessSimpleApiReferenceConversionAlreadyDone":false},"shared_onedriveforbusiness-1":{"connectionName":"shared-onedriveforbu-f0ff7c66-775c-4dfd-817b-69b9f6b8ad10","source":"Embedded","id":"/providers/Microsoft.PowerApps/apis/shared_onedriveforbusiness","tier":"NotSpecified","apiName":"onedriveforbusiness","isProcessSimpleApiReferenceConversionAlreadyDone":false},"shared_encodiangeneral-2":{"connectionName":"shared-encodiangener-cfb6d253-f141-47e5-a1d9-9cff1fe72648","source":"Embedded","id":"/providers/Microsoft.PowerApps/apis/shared_encodiangeneral","tier":"NotSpecified","apiName":"encodiangeneral","isProcessSimpleApiReferenceConversionAlreadyDone":false},"shared_sharepointonline":{"connectionName":"shared-sharepointonl-09ca80ee-2cf0-4734-9642-85c1234ec3c7","source":"Embedded","id":"/providers/Microsoft.PowerApps/apis/shared_sharepointonline","tier":"NotSpecified","apiName":"sharepointonline","isProcessSimpleApiReferenceConversionAlreadyDone":false}},"flowFailureAlertSubscribed":false,"isManaged":false}}